README.md
setup.py
mugan86_openwm_api.egg-info/PKG-INFO
mugan86_openwm_api.egg-info/SOURCES.txt
mugan86_openwm_api.egg-info/dependency_links.txt
mugan86_openwm_api.egg-info/top_level.txt
open_weather_api/__init__.py
open_weather_api/api.py
open_weather_api/config.py
open_weather_api/constants.py
open_weather_api/options/__init__.py
open_weather_api/options/city.py
open_weather_api/options/coordinates.py