Metadata-Version: 2.1
Name: mugan86-openwm-api
Version: 0.0.3
Summary: Obtenemos el tiempo seleccionado de una ubicación
Home-page: https://github.com/pypa/sampleproject
Author: Anartz Mugika Ledo
Author-email: mugan86@gmail.com
License: UNKNOWN
Project-URL: Bug Tracker, https://github.com/pypa/sampleproject/issues
Platform: UNKNOWN
Classifier: Programming Language :: Python :: 3
Classifier: License :: OSI Approved :: MIT License
Classifier: Operating System :: OS Independent
Requires-Python: >=3.6
